cphelper/__init__.py
cphelper/helpers.py
uthelper/__init__.py
uthelper/helpers.py
cp_upsolve_helper-0.0.2.dist-info/METADATA
cp_upsolve_helper-0.0.2.dist-info/WHEEL
cp_upsolve_helper-0.0.2.dist-info/licenses/LICENSE
cp_upsolve_helper-0.0.2.dist-info/RECORD
