Metadata-Version: 2.1
Name: cp-upsolve-helper
Version: 0.0.2
Summary: UT wrapper helpers for upsolving competitive programming questions
Project-URL: Homepage, https://github.com/kaashmonee/cp-upsolve-helper
Author-email: Skanda Kaashyap <skandakk@gmail.com>
License-File: LICENSE
Classifier: License :: OSI Approved :: MIT License
Classifier: Operating System :: OS Independent
Classifier: Programming Language :: Python :: 3
Requires-Python: >=3.8
